dume_api/__init__.py
dume_api-0.1.0.dist-info/METADATA
dume_api-0.1.0.dist-info/WHEEL
dume_api-0.1.0.dist-info/top_level.txt
dume_api-0.1.0.dist-info/RECORD
