Metadata-Version: 2.4
Name: dume-api
Version: 0.1.0
Summary: Helpers for scraping the DUME public procurement API
Author-email: Jonathan Soma <jonathan.soma@gmail.com>
License-Expression: MIT
Keywords: scraping,public procurement,dume
Requires-Python: >=3.9
Requires-Dist: requests>=2.31.0
